{"meta":{"title":"Let Everything that Has Breath","comment":"Matt Redman"},"paragraphs":[{"type":"chorus","lines":[{"text":"Let everything that","chords":{"0":"E"}},{"text":"Everything that","chords":{"0":"E/D#"}},{"text":"Everything that has breath praise the Lord (2x)","chords":{"0":"C#m7","17":"A","29":"A2/B"}}]},{"type":"default","lines":[{"text":"Praise you in the morning","chords":{"0":"E"}},{"text":"Praise you in the evening","chords":{"0":"E/D#"}},{"text":"Praise you when I'm young and when I'm old","chords":{"0":"C#m7","42":"A2"}},{"text":"Praise you when I'm laughing","chords":{"0":"E"}},{"text":"Praise you when I'm grieving","chords":{"0":"E/D#"}},{"text":"Praise you every season of the soul","chords":{"0":"C#m7"}}]},{"type":"default","lines":[{"text":"If we (they) could see how much you're worth","chords":{"4":"F#m7","28":"E/G#"}},{"text":"Your pow'r, Your might, Your endless love","chords":{"6":"F#m7","31":"E/G#"}},{"text":"Then surely we would never cease to praise ","chords":{"7":"F#m7","23":"E/G#","38":"A"}}]},{"type":"default","lines":[{"text":"Praise You in the heavens","chords":{}},{"text":"Joining with the angels","chords":{}},{"text":"Praising You forever and a day","chords":{}},{"text":"Praise You on the earth now","chords":{}},{"text":"Joining with creation","chords":{}},{"text":"Calling all the nations to Your praise","chords":{}}]}]}