{"meta":{"title":"All Heaven Declares","comment":"Noel & Tricia Richards\n(c)1987 Kingsway's Thankyou Music"},"paragraphs":[{"type":"default","lines":[{"text":"All heav'n declares ","chords":{"0":"A","11":"D","20":"Esus4"}},{"text":"The glory of the risen Lord","chords":{"4":"E","17":"D/A","23":"A"}},{"text":"Who can compare ","chords":{"11":"D","16":"Esus4"}},{"text":"With the beauty of the Lord?","chords":{"0":"E","16":"D/A","23":"A"}},{"text":"Forever he will be ","chords":{"16":"D","19":"E"}},{"text":"The Lamb upon the throne ","chords":{"18":"A","25":"F#m7"}},{"text":"I gladly bow my knee ","chords":{"16":"D","21":"E7"}},{"text":"And worship him alone ","chords":{"16":"A","22":"A"}}]},{"type":"default","lines":[{"text":"I will proclaim","chords":{}},{"text":"The glory of the risen Lord","chords":{}},{"text":"Who once was slain","chords":{}},{"text":"To reconcile us to God","chords":{}},{"text":"Forever you will be","chords":{}},{"text":"The Lamb upon the throne","chords":{}},{"text":"I gladly bow my knee","chords":{}},{"text":"And worship you alone","chords":{}}]}]}